AsteriskCommandApi/__init__.py
AsteriskCommandApi/atxfer.py
AsteriskCommandApi/clear_idle_call_actors.py
AsteriskCommandApi/core_show_channels.py
AsteriskCommandApi/get_agent_status.py
AsteriskCommandApi/get_info_anexos.py
AsteriskCommandApi/hangup.py
AsteriskCommandApi/originate.py
AsteriskCommandApi/queue_add.py
AsteriskCommandApi/queue_pause.py
AsteriskCommandApi/queue_remove.py
AsteriskCommandApi/queue_status.py
AsteriskCommandApi/queues.py
AsteriskCommandApi/redirect.py
AsteriskCommandApi/set_var.py
AsteriskCommandApi/sip_peers.py
AsteriskCommandApi/sip_peers_status.py
AsteriskCommandApi/commons/__init__.py
AsteriskCommandApi/commons/asterisk_action.py
AsteriskCommandApi/commons/asterisk_command.py
tests/__init__.py
tests/test_receive_commands.py
tests/commands/__init__.py
tests/commands/auxiliar_commands.py
tests/commands/test_atxfer_command.py
tests/commands/test_clear_idle_call_actors_command.py
tests/commands/test_core_show_channels_command.py
tests/commands/test_get_agent_status_command.py
tests/commands/test_get_info_anexos_command.py
tests/commands/test_hangup_command.py
tests/commands/test_originate_command.py
tests/commands/test_queue_add_command.py
tests/commands/test_queue_pause_command.py
tests/commands/test_queue_remove_command.py
tests/commands/test_queue_status_command.py
tests/commands/test_queues_command.py
tests/commands/test_redirect_command.py
tests/commands/test_set_var_command.py
tests/commands/test_sip_peers_command.py
tests/commands/test_sip_peers_status_command.py
cl3k_asteriskcommands-1.0.7.dist-info/METADATA
cl3k_asteriskcommands-1.0.7.dist-info/WHEEL
cl3k_asteriskcommands-1.0.7.dist-info/top_level.txt
cl3k_asteriskcommands-1.0.7.dist-info/RECORD
