Metadata-Version: 2.1
Name: cl3k-asteriskcommands
Version: 1.0.7
Summary: API for share asterisk commands beetween the micro services
Home-page: UNKNOWN
Author: Juares Vermelho Diaz (CL3k)
Author-email: jvermelho@cl3k.com
License: UNKNOWN
Keywords: Asterisk commands
Platform: UNKNOWN
